[
  {
    "input": [
      3,
      8,
      15,
      42,
      7
    ]
  },
  {
    "input": [
      25,
      13,
      47,
      89,
      33
    ]
  },
  {
    "input": [
      14,
      76,
      38,
      12,
      99,
      52
    ]
  },
  {
    "input": [
      60,
      23,
      89,
      12,
      45,
      77,
      31
    ]
  },
  {
    "input": [
      19,
      41,
      88,
      24,
      53,
      36,
      72,
      85
    ]
  },
  {
    "input": [
      5,
      91,
      48,
      16,
      73,
      27,
      62,
      10
    ]
  },
  {
    "input": [
      34,
      50,
      76,
      98,
      21,
      11,
      63,
      49,
      84,
      9
    ]
  },
  {
    "input": [
      18,
      92,
      43,
      7,
      68,
      56,
      14,
      29,
      71,
      33,
      100,
      65
    ]
  },
  {
    "input": [
      72,
      3,
      95,
      28,
      47,
      61,
      88,
      35,
      49,
      83,
      25,
      54
    ]
  },
  {
    "input": [
      40,
      18,
      93,
      61,
      7,
      45,
      67,
      83,
      91,
      25,
      53,
      36,
      11,
      77,
      89
    ]
  },
  {
    "input": [
      81,
      64,
      10,
      43,
      96,
      18,
      79,
      52,
      27,
      34,
      91,
      47,
      59,
      7,
      22,
      86,
      99
    ]
  },
  {
    "input": [
      14,
      32,
      76,
      49,
      25,
      83,
      62,
      11,
      18,
      41,
      91,
      73,
      67,
      36,
      27,
      58,
      100,
      8
    ]
  },
  {
    "input": [
      54,
      81,
      26,
      47,
      12,
      95,
      68,
      32,
      10,
      29,
      87,
      45,
      73,
      19,
      31,
      100,
      67,
      43,
      20
    ]
  }
]
